bciflow/__init__.py
bciflow/datasets/__init__.py
bciflow/datasets/attention.py
bciflow/datasets/bciciv2a.py
bciflow/datasets/bciciv2b.py
bciflow/datasets/cbcic.py
bciflow/datasets/dreams.py
bciflow/datasets/mengu.py
bciflow/modules/__init__.py
bciflow/modules/analysis/__init__.py
bciflow/modules/analysis/metric_functions.py
bciflow/modules/clf/__init__.py
bciflow/modules/clf/nbpw.py
bciflow/modules/core/__init__.py
bciflow/modules/core/kfold.py
bciflow/modules/core/util.py
bciflow/modules/fe/__init__.py
bciflow/modules/fe/apsd.py
bciflow/modules/fe/curvelength.py
bciflow/modules/fe/logpower.py
bciflow/modules/fe/nonlinearenergy.py
bciflow/modules/fe/welch_period.py
bciflow/modules/fs/__init__.py
bciflow/modules/fs/mibif.py
bciflow/modules/sf/__init__.py
bciflow/modules/sf/csp.py
bciflow/modules/sf/ea.py
bciflow/modules/tf/__init__.py
bciflow/modules/tf/emd_sift.py
bciflow/modules/tf/filterbank.py
bciflow/modules/tf/resample_cubic.py
bciflow/modules/tf/resample_fft.py
bciflow/modules/tf/wavelet.py
bciflow/modules/tf/bandpass/__init__.py
bciflow/modules/tf/bandpass/chebyshevII.py
bciflow/modules/tf/bandpass/convolution.py
bciflow-1.0.0.dev10.dist-info/METADATA
bciflow-1.0.0.dev10.dist-info/WHEEL
bciflow-1.0.0.dev10.dist-info/RECORD
