Metadata-Version: 2.4
Name: bciflow
Version: 1.0.0.dev10
Summary: A package for BCI-related tasks, including dataset loading, preprocessing, feature extraction, and classification.
Project-URL: Homepage, https://github.com/Lab-HC/bciflow
Project-URL: Issues, https://github.com/Lab-HC/bciflow/issues
Project-URL: Documentation, https://lab-hc.github.io/bciflow/
Author-email: Gabriel Henrique de Souza <gabriel.souza@ufjf.br>, Hiero Henrique Barcelos Costa <hiero.costa@estudante.ufjf.br>, Marcelo de Melo Amorim Filho <marcelomelo.amorim@estudante.ufjf.br>
Classifier: Development Status :: 3 - Alpha
Classifier: Intended Audience :: Customer Service
Classifier: Intended Audience :: Developers
Classifier: Intended Audience :: Education
Classifier: Intended Audience :: Healthcare Industry
Classifier: Intended Audience :: Science/Research
Classifier: Intended Audience :: Telecommunications Industry
Classifier: License :: OSI Approved :: GNU General Public License v3 (GPLv3)
Classifier: Programming Language :: Python :: 3
Requires-Python: >=3.7
Requires-Dist: emd
Requires-Dist: h5py
Requires-Dist: matplotlib
Requires-Dist: mne
Requires-Dist: numpy
Requires-Dist: pandas
Requires-Dist: pywavelets
Requires-Dist: scikit-learn
Requires-Dist: scipy
